examples/__init__.py
examples/fcm_2d.py
fuzzycmeans/__init__.py
fuzzycmeans/fuzzy_clustering.py
fuzzycmeans/visualization.py
tests/__init__.py
tests/test_notypical.py
tests/test_typical.py
fuzzycmeans-1.0.4.dist-info/LICENSE
fuzzycmeans-1.0.4.dist-info/METADATA
fuzzycmeans-1.0.4.dist-info/WHEEL
fuzzycmeans-1.0.4.dist-info/top_level.txt
fuzzycmeans-1.0.4.dist-info/RECORD
