Metadata-Version: 2.1
Name: fuzzycmeans
Version: 1.0.4
Summary: Fuzzy c-means according to the research paper by James C. Bezdek et. al
Home-page: https://github.com/oeg-upm/fuzzy-c-means
Author: Ahmad Alobaid
Author-email: aalobaid@fi.upm.es
Classifier: Programming Language :: Python :: 3.9
Classifier: License :: OSI Approved :: Apache Software License
Classifier: Operating System :: OS Independent
Classifier: Topic :: Scientific/Engineering :: Artificial Intelligence
Classifier: Topic :: Software Development :: Libraries
License-File: LICENSE
Requires-Dist: numpy
Requires-Dist: six
Requires-Dist: bokeh
